mcp_dingding/__init__.py
mcp_dingding/__main__.py
mcp_dingding/server.py
mcp_dingding-0.1.0.dist-info/METADATA
mcp_dingding-0.1.0.dist-info/WHEEL
mcp_dingding-0.1.0.dist-info/entry_points.txt
mcp_dingding-0.1.0.dist-info/RECORD
